{
  "viewports": [
    {
      "name": "phone",
      "width": 320,
      "height": 480
    },
    {
      "name": "tablet_small",
      "width": 480,
      "height": 768
    },
    {
      "name": "tablet",
      "width": 768,
      "height": 1024
    },
    {
      "name": "desktop",
      "width": 1024,
      "height": 768
    }
  ],
  "scenarios": [
    {
      "label": "Teasers",
      "url": "../../../build/components/teasers.html",
      "hideSelectors": [
        ".code",
        ".js-show-code"
      ],
      "removeSelectors": [],
      "selectors": [
        ".node-teaser-news",
        ".node-teaser-blog"
      ],
      "readyEvent": null,
      "delay": 500
    },
    {
      "label": "Forms",
      "url": "../../../build/components/forms.html",
      "hideSelectors": [],
      "removeSelectors": [],
      "selectors": [
        "#test-basic-form",
        "#test-horizontal-form"
      ],
      "readyEvent": null,
      "delay": 500
    }
  ]
}
